Workbook

Sheet Assumptions
A1: CharredGuard — Growth Model Assumptions
A2: Edit the yellow cells. Growth Curve and POAM sheets recalculate from these.
A4: Launch Date (Month 1 start) | B4: 46266
A5: On-Site Audit Price ($) | B5: 500
A6: Guided Self-Inspection Price ($) | B6: 200
A7: Avg Hardening Add-On Ticket ($) | B7: 450
A8: Hours per On-Site Audit (travel + visit + report) | B8: 4
A9: Hours per Guided Self-Inspection (review + report) | B9: 1
A10: Hours per Hardening Job (travel + materials + install) | B10: 4
A11: Sustainable Solo Delivery Hours / Week | B11: 25
A12: Weeks per Month (avg) | B12: 4.33
A14: Note: delivery-hour estimates and the 25 hr/wk sustainable-capacity figure are working assumptions, not measured data — adjust as real jobs give you actual timing.
A16: Path & Profitability Inputs
A17: Solo Part-Time Hours / Week (evenings, Paths B & C, and Path A before partner joins) | B17: 12
A18: Two-Person Full-Time Hours / Week (Path A, after partner joins) | B18: 45
A19: Partner Join Month (Path A trigger, 1-12) | B19: 6
A20: Audit / Self-Inspection Gross Margin (%) | B20: 0.9
A21: Hardening Add-On Gross Margin (%) | B21: 0.65
A22: Fixed Monthly Overhead ($) | B22: 223
A24: These three paths are the actual decision on the table, not just optimism levels. Path A assumes your business partner leaves their job once volume justifies it (Month 19 sets when); Path B keeps this a permanent evenings/weekends operation; Path C also stays part-time solo but drops the hardening add-on entirely, which sidesteps almost every open item in legal-risk-notes.md since there's no contractor-licensing exemption being relied on.

Sheet Growth Curve
A1: Year 1 Growth Curve & Solo-Capacity Check
A2: Volume targets are from the business plan's Year-1 projection. Hours/Capacity columns are computed live from the Assumptions sheet.
A4: Month # | B4: Target Month | C4: Audits | D4: Self-Inspections | E4: Hardening Jobs | F4: Revenue ($) | G4: Delivery Hours | H4: Hours / Week | I4: Capacity Status
A5: 1 | B5: =EDATE(Assumptions!$B$4,A5-1) | C5: 2 | D5: 1 | E5: 1 | F5: =C5*Assumptions!$B$5+D5*Assumptions!$B$6+E5*Assumptions!$B$7 | G5: =C5*Assumptions!$B$8+D5*Assumptions!$B$9+E5*Assumptions!$B$10 | H5: =G5/Assumptions!$B$12 | I5: =IF(H5>Assumptions!$B$11,"OVER CAPACITY — consider help","OK")
A6: 2 | B6: =EDATE(Assumptions!$B$4,A6-1) | C6: 3 | D6: 2 | E6: 1 | F6: =C6*Assumptions!$B$5+D6*Assumptions!$B$6+E6*Assumptions!$B$7 | G6: =C6*Assumptions!$B$8+D6*Assumptions!$B$9+E6*Assumptions!$B$10 | H6: =G6/Assumptions!$B$12 | I6: =IF(H6>Assumptions!$B$11,"OVER CAPACITY — consider help","OK")
A7: 3 | B7: =EDATE(Assumptions!$B$4,A7-1) | C7: 4 | D7: 2 | E7: 2 | F7: =C7*Assumptions!$B$5+D7*Assumptions!$B$6+E7*Assumptions!$B$7 | G7: =C7*Assumptions!$B$8+D7*Assumptions!$B$9+E7*Assumptions!$B$10 | H7: =G7/Assumptions!$B$12 | I7: =IF(H7>Assumptions!$B$11,"OVER CAPACITY — consider help","OK")
A8: 4 | B8: =EDATE(Assumptions!$B$4,A8-1) | C8: 5 | D8: 3 | E8: 2 | F8: =C8*Assumptions!$B$5+D8*Assumptions!$B$6+E8*Assumptions!$B$7 | G8: =C8*Assumptions!$B$8+D8*Assumptions!$B$9+E8*Assumptions!$B$10 | H8: =G8/Assumptions!$B$12 | I8: =IF(H8>Assumptions!$B$11,"OVER CAPACITY — consider help","OK")
A9: 5 | B9: =EDATE(Assumptions!$B$4,A9-1) | C9: 6 | D9: 3 | E9: 3 | F9: =C9*Assumptions!$B$5+D9*Assumptions!$B$6+E9*Assumptions!$B$7 | G9: =C9*Assumptions!$B$8+D9*Assumptions!$B$9+E9*Assumptions!$B$10 | H9: =G9/Assumptions!$B$12 | I9: =IF(H9>Assumptions!$B$11,"OVER CAPACITY — consider help","OK")
A10: 6 | B10: =EDATE(Assumptions!$B$4,A10-1) | C10: 8 | D10: 4 | E10: 3 | F10: =C10*Assumptions!$B$5+D10*Assumptions!$B$6+E10*Assumptions!$B$7 | G10: =C10*Assumptions!$B$8+D10*Assumptions!$B$9+E10*Assumptions!$B$10 | H10: =G10/Assumptions!$B$12 | I10: =IF(H10>Assumptions!$B$11,"OVER CAPACITY — consider help","OK")
A11: 7 | B11: =EDATE(Assumptions!$B$4,A11-1) | C11: 9 | D11: 4 | E11: 4 | F11: =C11*Assumptions!$B$5+D11*Assumptions!$B$6+E11*Assumptions!$B$7 | G11: =C11*Assumptions!$B$8+D11*Assumptions!$B$9+E11*Assumptions!$B$10 | H11: =G11/Assumptions!$B$12 | I11: =IF(H11>Assumptions!$B$11,"OVER CAPACITY — consider help","OK")
A12: 8 | B12: =EDATE(Assumptions!$B$4,A12-1) | C12: 10 | D12: 5 | E12: 4 | F12: =C12*Assumptions!$B$5+D12*Assumptions!$B$6+E12*Assumptions!$B$7 | G12: =C12*Assumptions!$B$8+D12*Assumptions!$B$9+E12*Assumptions!$B$10 | H12: =G12/Assumptions!$B$12 | I12: =IF(H12>Assumptions!$B$11,"OVER CAPACITY — consider help","OK")
A13: 9 | B13: =EDATE(Assumptions!$B$4,A13-1) | C13: 11 | D13: 5 | E13: 5 | F13: =C13*Assumptions!$B$5+D13*Assumptions!$B$6+E13*Assumptions!$B$7 | G13: =C13*Assumptions!$B$8+D13*Assumptions!$B$9+E13*Assumptions!$B$10 | H13: =G13/Assumptions!$B$12 | I13: =IF(H13>Assumptions!$B$11,"OVER CAPACITY — consider help","OK")
A14: 10 | B14: =EDATE(Assumptions!$B$4,A14-1) | C14: 12 | D14: 6 | E14: 5 | F14: =C14*Assumptions!$B$5+D14*Assumptions!$B$6+E14*Assumptions!$B$7 | G14: =C14*Assumptions!$B$8+D14*Assumptions!$B$9+E14*Assumptions!$B$10 | H14: =G14/Assumptions!$B$12 | I14: =IF(H14>Assumptions!$B$11,"OVER CAPACITY — consider help","OK")
A15: 11 | B15: =EDATE(Assumptions!$B$4,A15-1) | C15: 12 | D15: 6 | E15: 5 | F15: =C15*Assumptions!$B$5+D15*Assumptions!$B$6+E15*Assumptions!$B$7 | G15: =C15*Assumptions!$B$8+D15*Assumptions!$B$9+E15*Assumptions!$B$10 | H15: =G15/Assumptions!$B$12 | I15: =IF(H15>Assumptions!$B$11,"OVER CAPACITY — consider help","OK")
A16: 12 | B16: =EDATE(Assumptions!$B$4,A16-1) | C16: 14 | D16: 6 | E16: 6 | F16: =C16*Assumptions!$B$5+D16*Assumptions!$B$6+E16*Assumptions!$B$7 | G16: =C16*Assumptions!$B$8+D16*Assumptions!$B$9+E16*Assumptions!$B$10 | H16: =G16/Assumptions!$B$12 | I16: =IF(H16>Assumptions!$B$11,"OVER CAPACITY — consider help","OK")
B18: TOTAL | C18: =SUM(C5:C16) | D18: =SUM(D5:D16) | E18: =SUM(E5:E16) | F18: =SUM(F5:F16)

Sheet POAM
A1: CharredGuard — Plan of Action & Milestones (Year 1)
A3: ID | B3: Phase | C3: Milestone / Action | D3: Category | E3: Target Timing | F3: Owner | G3: Depends On | H3: Status | I3: Success Criteria / Notes
A4: 0.0 | B4: Phase 0 — Pre-Launch | C4: Decide operating path: (A) partner joins full-time once volume justifies it, (B) permanent part-time evenings solo, or (C) homeowner-inspections-only solo part-time (no hardening add-on) | D4: Planning | E4: Before Month 1 | F4: Matt (+ partner) | G4: — | H4: Not Started | I4: Decision documented — see 'Business Model Paths' tab. Determines whether hardening-related POAM items (1.3, 2.1) and legal-risk items 1/2/5/6 are even relevant.
A5: 0.1 | B5: Phase 0 — Pre-Launch | C5: Form California LLC (Articles of Organization) | D5: Legal | E5: Before Month 1 | F5: Matt | G5: — | H5: Not Started | I5: LLC registered with CA Secretary of State
A6: 0.2 | B6: Phase 0 — Pre-Launch | C6: Obtain EIN + open business bank account | D6: Financial | E6: Before Month 1 | F6: Matt | G6: 0.1 | H6: Not Started | I6: EIN issued, account open
A7: 0.3 | B7: Phase 0 — Pre-Launch | C7: Bind combined GL + E&O insurance policy | D7: Legal/Risk | E7: Before Month 1 | F7: Matt | G7: 0.1 | H7: Not Started | I7: Policy active, ~$145/mo confirmed
A8: 0.4 | B8: Phase 0 — Pre-Launch | C8: Attorney review of Inspection Agreement, Minor Work Contract, Liability Waiver (Section 9 templates) | D8: Legal | E8: Before Month 1 | F8: Matt + CA attorney | G8: — | H8: Not Started | I8: Written sign-off before any client signs a contract
A9: 0.5 | B9: Phase 0 — Pre-Launch | C9: Confirm hardening-work permit requirements per target city (Carlsbad, Escondido, Fallbrook, Ramona, Coto de Caza, Silverado Canyon, etc.) | D9: Legal/Compliance | E9: Before Month 1 | F9: Matt | G9: — | H9: Not Started | I9: B&P §7048 exemption requires NO permit — verify per city before offering hardening add-on
A10: 0.6 | B10: Phase 0 — Pre-Launch | C10: Confirm marketing/signage won't count as 'holding out as a contractor' under B&P §7048 | D10: Legal | E10: Before Month 1 | F10: Matt + CA attorney | G10: — | H10: Not Started | I10: Flagged risk: worksite banners + hardening-focused branding could void the minor-work exemption — get explicit guidance before Phase 2 signage/marketing
A11: 0.7 | B11: Phase 0 — Pre-Launch | C11: Begin NFPA CWMS certification study | D11: Certification | E11: Before Month 1 | F11: Matt | G11: — | H11: Not Started | I11: Exam scheduled
A12: 0.8 | B12: Phase 0 — Pre-Launch | C12: Website live with correct pricing ($500/$200) and SoCal geography | D12: Marketing | E12: Before Month 1 | F12: Matt | G12: — | H12: Done | I12: Completed — charred-guard-site updated
A13: 1.1 | B13: Phase 1 — Audit-Only Launch (M1-3) | C13: Deliver first paid on-site audit | D13: Ops | E13: Month 1 | F13: Matt | G13: 0.1-0.4 | H13: Not Started | I13: First $500 invoice paid
A14: 1.2 | B14: Phase 1 — Audit-Only Launch (M1-3) | C14: Deliver first guided self-inspection | D14: Ops | E14: Month 1 | F14: Matt | G14: 0.1-0.4 | H14: Not Started | I14: First $200 invoice paid
... A30: 4.4 | B30: Phase 4 — Scale & Year 2 Planning (M10-12) | C30: Draft Year 2 plan and budget | D30: Planning | E30: Month 12 | F30: Matt | G30: 4.3 | H30: Not Started | I30: Year 2 document drafted

Sheet Business Model Paths
A1: Which Path — Partner Joins Full-Time / Part-Time Evenings / Homeowner-Only
A2: Audits / Self / Hardening are editable per-path inputs (blue) — each path has a genuinely different volume story, not just a multiplier. Revenue, Hours/Week, and Capacity are formulas that recalc from the Assumptions tab.
C4: A — PARTNER JOINS FULL-TIME | I4: B — PART-TIME EVENINGS (SOLO, INDEFINITELY) | O4: C — HOMEOWNER INSPECTIONS ONLY (SOLO, PART-TIME, NO HARDENING)
A5: Month # | B5: Target Month | C5: Audits | D5: Self | E5: Hardening | F5: Revenue ($) | G5: Hrs/Wk | I5: Audits | J5: Self | K5: Hardening | L5: Revenue ($) | M5: Hrs/Wk | O5: Audits | P5: Self | Q5: Hardening | R5: Revenue ($) | S5: Hrs/Wk
A6: 1 | B6: ='Growth Curve'!B5 | C6: 1 | D6: 1 | E6: 0 | F6: =C6*Assumptions!$B$5+D6*Assumptions!$B$6+E6*Assumptions!$B$7 | G6: =(C6*Assumptions!$B$8+D6*Assumptions!$B$9+E6*Assumptions!$B$10)/Assumptions!$B$12 | I6: 1 | J6: 1 | K6: 0 | L6: =I6*Assumptions!$B$5+J6*Assumptions!$B$6+K6*Assumptions!$B$7 | M6: =(I6*Assumptions!$B$8+J6*Assumptions!$B$9+K6*Assumptions!$B$10)/Assumptions!$B$12 | O6: 1 | P6: 1 | Q6: 0 | R6: =O6*Assumptions!$B$5+P6*Assumptions!$B$6+Q6*Assumptions!$B$7 | S6: =(O6*Assumptions!$B$8+P6*Assumptions!$B$9+Q6*Assumptions!$B$10)/Assumptions!$B$12
A7: 2 | B7: ='Growth Curve'!B6 | C7: 2 | D7: 1 | E7: 0 | F7: =C7*Assumptions!$B$5+D7*Assumptions!$B$6+E7*Assumptions!$B$7 | G7: =(C7*Assumptions!$B$8+D7*Assumptions!$B$9+E7*Assumptions!$B$10)/Assumptions!$B$12 | I7: 1 | J7: 1 | K7: 0 | L7: =I7*Assumptions!$B$5+J7*Assumptions!$B$6+K7*Assumptions!$B$7 | M7: =(I7*Assumptions!$B$8+J7*Assumptions!$B$9+K7*Assumptions!$B$10)/Assumptions!$B$12 | O7: 2 | P7: 1 | Q7: 0 | R7: =O7*Assumptions!$B$5+P7*Assumptions!$B$6+Q7*Assumptions!$B$7 | S7: =(O7*Assumptions!$B$8+P7*Assumptions!$B$9+Q7*Assumptions!$B$10)/Assumptions!$B$12
A8: 3 | B8: ='Growth Curve'!B7 | C8: 2 | D8: 2 | E8: 1 | F8: =C8*Assumptions!$B$5+D8*Assumptions!$B$6+E8*Assumptions!$B$7 | G8: =(C8*Assumptions!$B$8+D8*Assumptions!$B$9+E8*Assumptions!$B$10)/Assumptions!$B$12 | I8: 2 | J8: 1 | K8: 1 | L8: =I8*Assumptions!$B$5+J8*Assumptions!$B$6+K8*Assumptions!$B$7 | M8: =(I8*Assumptions!$B$8+J8*Assumptions!$B$9+K8*Assumptions!$B$10)/Assumptions!$B$12 | O8: 2 | P8: 2 | Q8: 0 | R8: =O8*Assumptions!$B$5+P8*Assumptions!$B$6+Q8*Assumptions!$B$7 | S8: =(O8*Assumptions!$B$8+P8*Assumptions!$B$9+Q8*Assumptions!$B$10)/Assumptions!$B$12
A9: 4 | B9: ='Growth Curve'!B8 | C9: 3 | D9: 2 | E9: 1 | F9: =C9*Assumptions!$B$5+D9*Assumptions!$B$6+E9*Assumptions!$B$7 | G9: =(C9*Assumptions!$B$8+D9*Assumptions!$B$9+E9*Assumptions!$B$10)/Assumptions!$B$12 | I9: 2 | J9: 1 | K9: 1 | L9: =I9*Assumptions!$B$5+J9*Assumptions!$B$6+K9*Assumptions!$B$7 | M9: =(I9*Assumptions!$B$8+J9*Assumptions!$B$9+K9*Assumptions!$B$10)/Assumptions!$B$12 | O9: 3 | P9: 2 | Q9: 0 | R9: =O9*Assumptions!$B$5+P9*Assumptions!$B$6+Q9*Assumptions!$B$7 | S9: =(O9*Assumptions!$B$8+P9*Assumptions!$B$9+Q9*Assumptions!$B$10)/Assumptions!$B$12
A10: 5 | B10: ='Growth Curve'!B9 | C10: 3 | D10: 2 | E10: 1 | F10: =C10*Assumptions!$B$5+D10*Assumptions!$B$6+E10*Assumptions!$B$7 | G10: =(C10*Assumptions!$B$8+D10*Assumptions!$B$9+E10*Assumptions!$B$10)/Assumptions!$B$12 | I10: 2 | J10: 2 | K10: 1 | L10: =I10*Assumptions!$B$5+J10*Assumptions!$B$6+K10*Assumptions!$B$7 | M10: =(I10*Assumptions!$B$8+J10*Assumptions!$B$9+K10*Assumptions!$B$10)/Assumptions!$B$12 | O10: 3 | P10: 2 | Q10: 0 | R10: =O10*Assumptions!$B$5+P10*Assumptions!$B$6+Q10*Assumptions!$B$7 | S10: =(O10*Assumptions!$B$8+P10*Assumptions!$B$9+Q10*Assumptions!$B$10)/Assumptions!$B$12
A11: 6 | B11: ='Growth Curve'!B10 | C11: 6 | D11: 3 | E11: 2 | F11: =C11*Assumptions!$B$5+D11*Assumptions!$B$6+E11*Assumptions!$B$7 | G11: =(C11*Assumptions!$B$8+D11*Assumptions!$B$9+E11*Assumptions!$B$10)/Assumptions!$B$12 | I11: 2 | J11: 2 | K11: 1 | L11: =I11*Assumptions!$B$5+J11*Assumptions!$B$6+K11*Assumptions!$B$7 | M11: =(I11*Assumptions!$B$8+J11*Assumptions!$B$9+K11*Assumptions!$B$10)/Assumptions!$B$12 | O11: 3 | P11: 3 | Q11: 0 | R11: =O11*Assumptions!$B$5+P11*Assumptions!$B$6+Q11*Assumptions!$B$7 | S11: =(O11*Assumptions!$B$8+P11*Assumptions!$B$9+Q11*Assumptions!$B$10)/Assumptions!$B$12
A12: 7 | B12: ='Growth Curve'!B11 | C12: 8 | D12: 4 | E12: 3 | F12: =C12*Assumptions!$B$5+D12*Assumptions!$B$6+E12*Assumptions!$B$7 | G12: =(C12*Assumptions!$B$8+D12*Assumptions!$B$9+E12*Assumptions!$B$10)/Assumptions!$B$12 | I12: 3 | J12: 2 | K12: 1 | L12: =I12*Assumptions!$B$5+J12*Assumptions!$B$6+K12*Assumptions!$B$7 | M12: =(I12*Assumptions!$B$8+J12*Assumptions!$B$9+K12*Assumptions!$B$10)/Assumptions!$B$12 | O12: 4 | P12: 3 | Q12: 0 | R12: =O12*Assumptions!$B$5+P12*Assumptions!$B$6+Q12*Assumptions!$B$7 | S12: =(O12*Assumptions!$B$8+P12*Assumptions!$B$9+Q12*Assumptions!$B$10)/Assumptions!$B$12
A13: 8 | B13: ='Growth Curve'!B12 | C13: 9 | D13: 4 | E13: 4 | F13: =C13*Assumptions!$B$5+D13*Assumptions!$B$6+E13*Assumptions!$B$7 | G13: =(C13*Assumptions!$B$8+D13*Assumptions!$B$9+E13*Assumptions!$B$10)/Assumptions!$B$12 | I13: 3 | J13: 2 | K13: 1 | L13: =I13*Assumptions!$B$5+J13*Assumptions!$B$6+K13*Assumptions!$B$7 | M13: =(I13*Assumptions!$B$8+J13*Assumptions!$B$9+K13*Assumptions!$B$10)/Assumptions!$B$12 | O13: 4 | P13: 3 | Q13: 0 | R13: =O13*Assumptions!$B$5+P13*Assumptions!$B$6+Q13*Assumptions!$B$7 | S13: =(O13*Assumptions!$B$8+P13*Assumptions!$B$9+Q13*Assumptions!$B$10)/Assumptions!$B$12
A14: 9 | B14: ='Growth Curve'!B13 | C14: 10 | D14: 5 | E14: 4 | F14: =C14*Assumptions!$B$5+D14*Assumptions!$B$6+E14*Assumptions!$B$7 | G14: =(C14*Assumptions!$B$8+D14*Assumptions!$B$9+E14*Assumptions!$B$10)/Assumptions!$B$12 | I14: 4 | J14: 2 | K14: 1 | L14: =I14*Assumptions!$B$5+J14*Assumptions!$B$6+K14*Assumptions!$B$7 | M14: =(I14*Assumptions!$B$8+J14*Assumptions!$B$9+K14*Assumptions!$B$10)/Assumptions!$B$12 | O14: 4 | P14: 3 | Q14: 0 | R14: =O14*Assumptions!$B$5+P14*Assumptions!$B$6+Q14*Assumptions!$B$7 | S14: =(O14*Assumptions!$B$8+P14*Assumptions!$B$9+Q14*Assumptions!$B$10)/Assumptions!$B$12
A15: 10 | B15: ='Growth Curve'!B14 | C15: 11 | D15: 5 | E15: 5 | F15: =C15*Assumptions!$B$5+D15*Assumptions!$B$6+E15*Assumptions!$B$7 | G15: =(C15*Assumptions!$B$8+D15*Assumptions!$B$9+E15*Assumptions!$B$10)/Assumptions!$B$12 | I15: 4 | J15: 2 | K15: 1 | L15: =I15*Assumptions!$B$5+J15*Assumptions!$B$6+K15*Assumptions!$B$7 | M15: =(I15*Assumptions!$B$8+J15*Assumptions!$B$9+K15*Assumptions!$B$10)/Assumptions!$B$12 | O15: 5 | P15: 3 | Q15: 0 | R15: =O15*Assumptions!$B$5+P15*Assumptions!$B$6+Q15*Assumptions!$B$7 | S15: =(O15*Assumptions!$B$8+P15*Assumptions!$B$9+Q15*Assumptions!$B$10)/Assumptions!$B$12
A16: 11 | B16: ='Growth Curve'!B15 | C16: 12 | D16: 6 | E16: 5 | F16: =C16*Assumptions!$B$5+D16*Assumptions!$B$6+E16*Assumptions!$B$7 | G16: =(C16*Assumptions!$B$8+D16*Assumptions!$B$9+E16*Assumptions!$B$10)/Assumptions!$B$12 | I16: 4 | J16: 2 | K16: 1 | L16: =I16*Assumptions!$B$5+J16*Assumptions!$B$6+K16*Assumptions!$B$7 | M16: =(I16*Assumptions!$B$8+J16*Assumptions!$B$9+K16*Assumptions!$B$10)/Assumptions!$B$12 | O16: 5 | P16: 3 | Q16: 0 | R16: =O16*Assumptions!$B$5+P16*Assumptions!$B$6+Q16*Assumptions!$B$7 | S16: =(O16*Assumptions!$B$8+P16*Assumptions!$B$9+Q16*Assumptions!$B$10)/Assumptions!$B$12
A17: 12 | B17: ='Growth Curve'!B16 | C17: 13 | D17: 6 | E17: 6 | F17: =C17*Assumptions!$B$5+D17*Assumptions!$B$6+E17*Assumptions!$B$7 | G17: =(C17*Assumptions!$B$8+D17*Assumptions!$B$9+E17*Assumptions!$B$10)/Assumptions!$B$12 | I17: 4 | J17: 3 | K17: 1 | L17: =I17*Assumptions!$B$5+J17*Assumptions!$B$6+K17*Assumptions!$B$7 | M17: =(I17*Assumptions!$B$8+J17*Assumptions!$B$9+K17*Assumptions!$B$10)/Assumptions!$B$12 | O17: 5 | P17: 4 | Q17: 0 | R17: =O17*Assumptions!$B$5+P17*Assumptions!$B$6+Q17*Assumptions!$B$7 | S17: =(O17*Assumptions!$B$8+P17*Assumptions!$B$9+Q17*Assumptions!$B$10)/Assumptions!$B$12
A19: Year-1 Summary
A20: Metric | B20: A — Partner Joins | C20: B — Evenings Only | D20: C — Homeowner-Only
A21: Total Audits | B21: =SUM(C6:C17) | C21: =SUM(I6:I17) | D21: =SUM(O6:O17)
A22: Total Self-Inspections | B22: =SUM(D6:D17) | C22: =SUM(J6:J17) | D22: =SUM(P6:P17)
A23: Total Hardening Jobs | B23: =SUM(E6:E17) | C23: =SUM(K6:K17) | D23: =SUM(Q6:Q17)
A24: Total Revenue ($) | B24: =SUM(F6:F17) | C24: =SUM(L6:L17) | D24: =SUM(R6:R17)
A25: Est. Year-1 Net Profit ($) | B25: =(SUMPRODUCT(C6:C17,Assumptions!$B$5)+SUMPRODUCT(D6:D17,Assumptions!$B$6))*Assumptions!$B$20+(SUMPRODUCT(E6:E17,Assumptions!$B$7))*Assumptions!$B$21-12*Assumptions!$B$22 | C25: =(SUMPRODUCT(I6:I17,Assumptions!$B$5)+SUMPRODUCT(J6:J17,Assumptions!$B$6))*Assumptions!$B$20+(SUMPRODUCT(K6:K17,Assumptions!$B$7))*Assumptions!$B$21-12*Assumptions!$B$22 | D25: =(SUMPRODUCT(O6:O17,Assumptions!$B$5)+SUMPRODUCT(P6:P17,Assumptions!$B$6))*Assumptions!$B$20+(SUMPRODUCT(Q6:Q17,Assumptions!$B$7))*Assumptions!$B$21-12*Assumptions!$B$22
A26: Peak Month Hours/Week | B26: =MAX(G6:G17) | C26: =MAX(M6:M17) | D26: =MAX(S6:S17)
A27: Capacity Threshold (Peak Month, hrs/wk) | B27: =IF(12>=Assumptions!$B$19,Assumptions!$B$18,Assumptions!$B$17) | C27: =Assumptions!$B$17 | D27: =Assumptions!$B$17
A29: Path A's threshold uses Month 12 (post-join) for comparison since that's the relevant capacity once the partner is in full-time; check earlier months against the solo rate if you want the pre-join capacity picture. Legal note: Path C drops hardening entirely, which means almost every open item in legal-risk-notes.md (contractor-licensing exemption, permits, marketing-as-contractor risk) becomes moot — there's no physical contracting work to license at all.
